{"cameraMode":{"drawMode":0,"name":"Shaded","section":"Shading Mode"},"sceneLighting":false,"audioPlay":false,"sceneViewState":{"showFog":true,"showMaterialUpdate":false,"showSkybox":false,"showFlares":true,"showImageEffects":true,"showParticleSystems":true,"showVisualEffectGraphs":true,"m_FxEnabled":false},"in2DMode":false,"pivot":{"x":0.5898007750511169,"y":1.2797563076019288,"z":6.353878021240234},"rotation":{"x":0.24701698124408723,"y":-0.6349449753761292,"z":0.22518324851989747,"w":0.696513831615448},"size":2.0089478492736818,"orthographic":false}